crdl/__init__.py
crdl/api.py
crdl/cli.py
crdl/config.py
crdl/downloader.py
crdl/drm_utils.py
crdl/media_utils.py
crdl/version.py
crdl-0.0.8.dist-info/licenses/LICENSE
crdl-0.0.8.dist-info/METADATA
crdl-0.0.8.dist-info/WHEEL
crdl-0.0.8.dist-info/entry_points.txt
crdl-0.0.8.dist-info/top_level.txt
crdl-0.0.8.dist-info/RECORD
