Metadata-Version: 2.4
Name: crdl
Version: 0.0.8
Summary: A simple crunchyroll downloader
Author-email: TanmoyTheBoT <tanmoysarkershuvo@gmail.com>
License: MIT
Project-URL: Homepage, https://github.com/TanmoyTheBoT/crdl
Classifier: Programming Language :: Python :: 3
Classifier: License :: OSI Approved :: MIT License
Classifier: Operating System :: OS Independent
Requires-Python: >=3.8
License-File: LICENSE
Requires-Dist: cloudscraper
Requires-Dist: pywidevine
Requires-Dist: requests
Dynamic: license-file
